processor_skeleton/processor/mux2.sv
`ifndef MUX2
`define MUX2


//based on marano implementation of ottobit cpu

module mux2 #(parameter DWIDTH = 8)(
    input  logic [DWIDTH-1:0] d0, d1, 
    input  logic              s, 
    output logic [DWIDTH-1:0] y
);

  assign y = s ? d0 : d1; 
endmodule

`endif // MUX2

processor_skeleton/processor/adder.sv
`ifndef ADDER
`define ADDER

module adder #(parameter DWIDTH = 8)(
    input  logic [DWIDTH-1:0] a, b,
    output logic [DWIDTH-1:0] y
);

  assign y = a + b;
endmodule

`endif // ADDER

processor_skeleton/processor/sl2.sv
`ifndef SL2
`define SL2

// Shift left 2 bits
module sl2 #(parameter DWIDTH = 8)(
    input  logic [DWIDTH-1:0] a,
    output logic [DWIDTH-1:0] y
);

  // shift left by 2
  assign y = {a[DWIDTH-3:0], 2'b00};
endmodule

`endif // SL2

processor_skeleton/processor_testing/datapath/flopr.sv
`ifndef FLOPR
`define FLOPR

module flopr #(parameter DWIDTH = 8)(
    input  logic             clk, reset,
    input  logic [DWIDTH-1:0] d, 
    output logic [DWIDTH-1:0] q
);

  always @(posedge clk, posedge reset)
    if (reset) q <= 0;
    else       q <= d;
endmodule

`endif // FLOPR

processor_skeleton/processor_testing/datapath/alu.sv
`ifndef ALU
`define ALU

// ALU with 4-bit operands
module alu #(parameter WIDTH = 8)(
    input  logic clk,
    input  logic [WIDTH-1:0] a, b,
    input  logic [2:0] alucontrol,      // alucontrol signal is 3 bits
    output logic [WIDTH-1:0] result,    // ALUout of WIDTH bits
    output logic       zero             // ZERO flag
);

  
  reg [WIDTH-1: 0] Rzero = 0;
  

  

  always @*
    case (alucontrol)
      4'b0000: result = a + b; //and
      4'b0001: result = a - b; //sub
      4'b0010: result = a & b; //and
      4'b0011: result = a | b; //or
      4'b0100: result = !(a | b); //nor
      4'b0101: result = a ^ b; //xor
      4'b0110 : result = a / b ; //div
      4'b0111 : result = (a < b) ? 1'b1:1'b0; //slt
      4'b1000: result = a << b; //LSL
      4'b1001 : result = a >> b; //LSR
    endcase

  assign zero = (result == Rzero); // similar to 32'b0
endmodule

`endif // ALU

processor_skeleton/processor/signext.sv
`ifndef SIGNEXT
`define SIGNEXT


//based on marano implementation of ottobit cpu

module signext #(parameter DWIDTH = 8)(
    input  logic [6:0] a,
    output logic [DWIDTH-1:0] y
);
              
  assign y = {{DWIDTH{a[6]}}, a};
endmodule

`endif // SIGNEXT

processor_skeleton/processor_testing/datapath/regfile.sv
`ifndef REGFILE
`define REGFILE

module regfile #(parameter DWIDTH = 8, RWIDTH = 3, REGNUM = 8)(
    input  logic              clk, 
    input  logic              we3, 
    input  logic [RWIDTH-1:0] ra1, ra2, wa3, 
    input  logic [DWIDTH-1:0] wd3, 
    output logic [DWIDTH-1:0] rd1, rd2
);

  logic [DWIDTH-1:0] rf[REGNUM-1:0]; // REGNUM registers of data of DWIDTH bits wide

  initial
    rf[0] = {REGNUM{1'b0}}; // Rz (Zero Register) is constant value of 0
                            // setting value of zero using Verilog concatenation.

  // three ported register file
  // read two ports combinationally
  // write third port on rising edge of clk
  // register 0 hardwired to 0
  // note: for pipelined processor, write third port
  // on falling edge of clk

  always @(posedge clk)
    if (we3)
    begin
      $display("writing to register %h value %d",wa3,wd3);
      if (wa3 != 0)
      begin
        rf[wa3] <= wd3;
      end
    end

  assign rd1 = (ra1 != 0) ? rf[ra1] : 0;
  assign rd2 = (ra2 != 0) ? rf[ra2] : 0;
endmodule

`endif //REGFILE

processor_skeleton/processor_testing/datapath/datapath.sv
`ifndef DATAPATH
`define DATAPATH

module datapath #(parameter DWIDTH = 8, IWIDTH = 16)(
    input  logic              clk, reset,
    input  logic              memtoreg, pcsrc,
    input  logic              alusrc, regdst,
    input  logic              regwrite, jump,
    input  logic [2:0]        alucontrol,
    output logic              zero,
    output logic [DWIDTH-1:0] pc,
    input  logic [IWIDTH-1:0] instr,
    output logic [DWIDTH-1:0] aluout, writedata,
    input  logic [DWIDTH-1:0] readdata
);

  logic [2:0]  writereg; // we have 8 registers addressed by 3 bits
  logic [DWIDTH-1:0] pcnext, pcnextbr, pcplus2, pcbranch;
  logic [DWIDTH-1:0] signimm, signimmsh;
  logic [DWIDTH-1:0] srca, srcb;
  logic [DWIDTH-1:0] result;
  logic [DWIDTH-1:0] addTwoBytesToPC = {DWIDTH{1'b0}} + 2; 

  // next PC logic

  mux2 wrmux(instr[7:6], instr[9:8], regdst,writereg); //set write for I-type or R-type
  regfile rf(clk, regwrite, instr[11:10],instr[9:8],writereg, result, srca, writedata);
  mux2 resmux(aluout,readdata,memtoreg,result);
  signext se(instr[15:0],signimm); //I or R

  mux2 srcbmux (writedata,signimm,alusrc,srcb); //I or R
  alu alu(srca,srcab,alucontrol, aluout,zero);

  pcsrc = branch & zero;


  flopr #(DWIDTH) pcreg(clk, reset, pcnext, pc);
  adder #(DWIDTH) pcadd1(pc, addTwoBytesToPC, pcplus2);
  
  sl2   #(DWIDTH) immsh(signimm, signimmsh);
  adder #(DWIDTH) pcadd2(pcplus2, signimmsh, pcbranch);
  mux2  #(DWIDTH) pcbrmux(pcplus2, pcbranch, pcsrc, pcnextbr);
  mux2  #(DWIDTH) pcmux(pcnextbr, {instr[7:0]}, jump, pcnext);
  // instr[7:0] according to ISA should be instr[11:0] for the 13-bit jump address BUT
  // instr[11:0] means 12-bit address to do an unconditional jump; PC = jump address
  // FYI we do not have enough memory with an 8-bit CPU with byte addressing to use this.

endmodule

`endif // DATAPATH

processor_skeleton/processor_testing/datapath/datapath_tb.sv
module test #(parameter DWIDTH = 8, IWIDTH = 16)();

    reg clk;
    reg reset;
    reg memtoreg;
    reg branch;
    reg alusrc;
    reg regdst;
    reg regwrite;
    reg jump;
    reg [3:0] alucontrol;
    wire pcsrc;
    wire zero;
    wire [DWIDTH-1:0] pc;
    reg [IWIDTH-1:0] instr;
    wire [DWIDTH-1:0] aluout;
    wire [DWIDTH-1:0] writedata;
    reg [DWIDTH-1:0] readdata;

    datapath datapath(
        .clk(clk),
        .reset(reset),
        .memtoreg(memtoreg),
        .branch(branch),
        .alusrc(alusrc),
        .regdst(regdst),
        .regwrite(regwrite),
        .jump(jump),
        .alucontrol(alucontrol),
        .pcsrc(pcsrc),
        .zero(zero),
        .pc(pc),
        .instr(instr),
        .aluout(aluout),
        .writedata(writedata),
        .readdata(readdata));
    
      // generate the clock

  initial begin
    clk = 1'b0;
    forever #1 clk = ~clk;
  end

  // Generate the reset
  initial begin

   reset = 1'b1;
    #10
   reset = 1'b0;
  end
  // Test stimulus
  initial begin
    // Use the monitor task to display the FPGA IO

    $dumpfile("datapath_tb.vcd");
    $dumpvars(0,clk,reset,memtoreg,branch,alusrc,regdst,regwrite, jump,alucontrol,pcsrc,zero,
    pc,instr, aluout, writedata,readdata);

    $monitor("time=%3d, aluout=%b, writedata=%b, zero=%b \n",
              $time, aluout, writedata, zero);
 
    // Generate each input with a 20 ns delay between them

    //I-type - ADDI
    regwrite = 1'b1;
    regdst = 1'b0;
    memtoreg = 1'b0;
    branch = 1'b0;
    alusrc = 1'b1;
    jump = 1'b0;
    alucontrol = 4'b0000;
    readdata = 8'b00000000;
    instr = 16'b1100001000000001;

    #20;

    regwrite = 1'b1;
    regdst = 1'b0;
    memtoreg = 1'b0;
    branch = 1'b0;
    alusrc = 1'b1;
    jump = 1'b0;
    alucontrol = 4'b0000;
    readdata = 8'b00000000;
    instr = 16'b1100101100000010;

    

    #20;

    
  end



endmodule

processor_skeleton/processor_testing/datapath/datapath_tb.vcd
$date
	Sun May 15 15:46:12 2022
$end
$version
	Icarus Verilog
$end
$timescale
	1s
$end
$scope module test $end
$var reg 1 ! clk $end
$upscope $end
$scope module test $end
$var reg 1 " reset $end
$upscope $end
$scope module test $end
$var reg 1 # memtoreg $end
$upscope $end
$scope module test $end
$var reg 1 $ branch $end
$upscope $end
$scope module test $end
$var reg 1 % alusrc $end
$upscope $end
$scope module test $end
$var reg 1 & regdst $end
$upscope $end
$scope module test $end
$var reg 1 ' regwrite $end
$upscope $end
$scope module test $end
$var reg 1 ( jump $end
$upscope $end
$scope module test $end
$var reg 4 ) alucontrol [3:0] $end
$upscope $end
$scope module test $end
$var wire 1 * pcsrc $end
$upscope $end
$scope module test $end
$var wire 1 + zero $end
$upscope $end
$scope module test $end
$var wire 8 , pc [7:0] $end
$upscope $end
$scope module test $end
$var reg 16 - instr [15:0] $end
$upscope $end
$scope module test $end
$var wire 8 . aluout [7:0] $end
$upscope $end
$scope module test $end
$var wire 8 / writedata [7:0] $end
$upscope $end
$scope module test $end
$var reg 8 0 readdata [7:0] $end
$upscope $end
$enddefinitions $end
#0
$dumpvars
b0 0
bx /
b1 .
b1100001000000001 -
b0 ,
0+
0*
b0 )
0(
1'
0&
1%
0$
0#
1"
0!
$end
#1
b1 /
1!
#2
0!
#3
1!
#4
0!
#5
1!
#6
0!
#7
1!
#8
0!
#9
1!
#10
0!
0"
#11
b10 ,
1!
#12
0!
#13
b100 ,
1!
#14
0!
#15
b110 ,
1!
#16
0!
#17
b1000 ,
1!
#18
0!
#19
b1010 ,
1!
#20
b11 .
bx /
0!
b1100101100000010 -
#21
b11 /
b1100 ,
1!
#22
0!
#23
b1110 ,
1!
#24
0!
#25
b10000 ,
1!
#26
0!
#27
b10010 ,
1!
#28
0!
#29
b10100 ,
1!
#30
0!
#31
b10110 ,
1!
#32
0!
#33
b11000 ,
1!
#34
0!
#35
b11010 ,
1!
#36
0!
#37
b11100 ,
1!
#38
0!
#39
b11110 ,
1!
#40
0!
#41
b100000 ,
1!
#42
0!
#43
b100010 ,
1!
#44
0!
#45
b100100 ,
1!
#46
0!
#47
b100110 ,
1!
#48
0!
#49
b101000 ,
1!
#50
0!
#51
b101010 ,
1!
#52
0!
#53
b101100 ,
1!
#54
0!
#55
b101110 ,
1!
#56
0!
#57
b110000 ,
1!
#58
0!
#59
b110010 ,
1!
#60
0!
#61
b110100 ,
1!
#62
0!
#63
b110110 ,
1!
#64
0!
#65
b111000 ,
1!
#66
0!
#67
b111010 ,
1!
#68
0!
#69
b111100 ,
1!
#70
0!
#71
b111110 ,
1!
#72
0!
#73
b1000000 ,
1!
#74
0!
#75
b1000010 ,
1!
#76
0!
#77
b1000100 ,
1!
#78
0!
#79
b1000110 ,
1!
#80
0!
#81
b1001000 ,
1!
#82
0!
#83
b1001010 ,
1!
#84
0!
#85
b1001100 ,
1!
#86
0!
#87
b1001110 ,
1!
#88
0!
#89
b1010000 ,
1!
#90
0!
#91
b1010010 ,
1!
#92
0!
#93
b1010100 ,
1!
#94
0!
#95
b1010110 ,
1!
#96
0!
#97
b1011000 ,
1!
#98
0!
#99
b1011010 ,
1!
#100
0!
#101
b1011100 ,
1!
#102
0!
#103
b1011110 ,
1!
#104
0!
#105
b1100000 ,
1!
#106
0!
#107
b1100010 ,
1!
#108
0!
#109
b1100100 ,
1!
#110
0!
#111
b1100110 ,
1!
#112
0!
#113
b1101000 ,
1!
#114
0!
#115
b1101010 ,
1!
#116
0!
#117
b1101100 ,
1!
#118
0!
#119
b1101110 ,
1!
#120
0!
#121
b1110000 ,
1!
#122
0!
#123
b1110010 ,
1!
#124
0!
#125
b1110100 ,
1!
#126
0!
#127
b1110110 ,
1!
#128
0!
#129
b1111000 ,
1!
#130
0!
#131
b1111010 ,
1!
#132
0!
#133
b1111100 ,
1!
#134
0!
#135
b1111110 ,
1!
#136
0!
#137
b10000000 ,
1!
#138
0!
#139
b10000010 ,
1!
#140
0!
#141
b10000100 ,
1!
#142
0!
#143
b10000110 ,
1!
#144
0!
#145
b10001000 ,
1!
#146
0!
#147
b10001010 ,
1!
#148
0!
#149
b10001100 ,
1!
#150
0!
#151
b10001110 ,
1!
#152
0!
#153
b10010000 ,
1!
#154
0!
#155
b10010010 ,
1!
#156
0!
#157
b10010100 ,
1!
#158
0!
#159
b10010110 ,
1!
#160
0!
#161
b10011000 ,
1!
#162
0!
#163
b10011010 ,
1!
#164
0!
#165
b10011100 ,
1!
#166
0!
#167
b10011110 ,
1!
#168
0!
#169
b10100000 ,
1!
#170
0!
#171
b10100010 ,
1!
#172
0!
#173
b10100100 ,
1!
#174
0!
#175
b10100110 ,
1!
#176
0!
#177
b10101000 ,
1!
#178
0!
#179
b10101010 ,
1!
#180
0!
#181
b10101100 ,
1!
#182
0!
#183
b10101110 ,
1!
#184
0!
#185
b10110000 ,
1!
#186
0!
#187
b10110010 ,
1!
#188
0!
#189
b10110100 ,
1!
#190
0!
#191
b10110110 ,
1!
#192
0!
#193
b10111000 ,
1!
#194
0!
#195
b10111010 ,
1!
#196
0!
#197
b10111100 ,
1!
#198
0!
#199
b10111110 ,
1!
#200
0!
#201
b11000000 ,
1!
#202
0!
#203
b11000010 ,
1!
#204
0!
#205
b11000100 ,
1!
#206
0!
#207
b11000110 ,
1!
#208
0!
#209
b11001000 ,
1!
#210
0!
#211
b11001010 ,
1!
#212
0!
#213
b11001100 ,
1!
#214
0!
#215
b11001110 ,
1!
#216
0!
#217
b11010000 ,
1!
#218
0!
#219
b11010010 ,
1!
#220
0!
#221
b11010100 ,
1!
#222
0!
#223
b11010110 ,
1!
#224
0!
#225
b11011000 ,
1!
#226
0!
#227
b11011010 ,
1!
#228
0!
#229
b11011100 ,
1!
#230
0!
#231
b11011110 ,
1!
#232
0!
#233
b11100000 ,
1!
#234
0!
#235
b11100010 ,
1!
#236
0!
#237
b11100100 ,
1!
#238
0!
#239
b11100110 ,
1!
#240
0!
#241
b11101000 ,
1!
#242
0!
#243
b11101010 ,
1!
#244
0!
#245
b11101100 ,
1!
#246
0!
#247
b11101110 ,
1!
#248
0!
#249
b11110000 ,
1!
#250
0!
#251
b11110010 ,
1!
#252
0!
#253
b11110100 ,
1!
#254
0!
#255
b11110110 ,
1!
#256
0!
#257
b11111000 ,
1!
#258
0!
#259
b11111010 ,
1!
#260
0!
#261
b11111100 ,
1!
#262
0!
#263
b11111110 ,
1!
#264
0!
#265
b0 ,
1!
#266
0!
#267
b10 ,
1!
#268
0!
#269
b100 ,
1!
#270
0!
#271
b110 ,
1!
#272
0!
#273
b1000 ,
1!
#274
0!
#275
b1010 ,
1!
#276
0!
#277
b1100 ,
1!
#278
0!
#279
b1110 ,
1!
#280
0!
#281
b10000 ,
1!
#282
0!
#283
b10010 ,
1!
#284
0!
#285
b10100 ,
1!
#286
0!
#287
b10110 ,
1!
#288
0!
#289
b11000 ,
1!
#290
0!
#291
b11010 ,
1!
#292
0!
#293
b11100 ,
1!
#294
0!
#295
b11110 ,
1!
#296
0!
#297
b100000 ,
1!
#298
0!
#299
b100010 ,
1!
#300
0!
#301
b100100 ,
1!
#302
0!
#303
b100110 ,
1!
#304
0!
#305
b101000 ,
1!
#306
0!
#307
b101010 ,
1!
#308
0!
#309
b101100 ,
1!
#310
0!
#311
b101110 ,
1!
#312
0!
#313
b110000 ,
1!
#314
0!
#315
b110010 ,
1!
#316
0!
#317
b110100 ,
1!
#318
0!
#319
b110110 ,
1!
#320
0!
#321
b111000 ,
1!
#322
0!
#323
b111010 ,
1!
#324
0!
#325
b111100 ,
1!
#326
0!
#327
b111110 ,
1!
#328
0!
#329
b1000000 ,
1!
#330
0!
#331
b1000010 ,
1!
#332
0!
#333
b1000100 ,
1!
#334
0!
#335
b1000110 ,
1!
#336
0!
#337
b1001000 ,
1!
#338
0!
#339
b1001010 ,
1!
#340
0!
#341
b1001100 ,
1!
#342
0!
#343
b1001110 ,
1!
#344
0!
#345
b1010000 ,
1!
#346
0!
#347
b1010010 ,
1!
#348
0!
#349
b1010100 ,
1!
#350
0!
#351
b1010110 ,
1!
#352
0!
#353
b1011000 ,
1!
#354
0!
#355
b1011010 ,
1!
#356
0!
#357
b1011100 ,
1!
#358
0!
#359
b1011110 ,
1!
#360
0!
#361
b1100000 ,
1!
#362
0!
#363
b1100010 ,
1!
#364
0!
#365
b1100100 ,
1!
#366
0!
#367
b1100110 ,
1!
#368
0!
#369
b1101000 ,
1!
#370
0!
#371
b1101010 ,
1!
#372
0!
#373
b1101100 ,
1!
#374
0!
#375
b1101110 ,
1!
#376
0!
#377
b1110000 ,
1!
#378
0!
#379
b1110010 ,
1!
#380
0!
#381
b1110100 ,
1!
#382
0!
#383
b1110110 ,
1!
#384
0!
#385
b1111000 ,
1!
#386
0!
#387
b1111010 ,
1!
#388
0!
#389
b1111100 ,
1!
#390
0!
#391
b1111110 ,
1!
#392
0!
#393
b10000000 ,
1!
#394
0!
#395
b10000010 ,
1!
#396
0!
#397
b10000100 ,
1!
#398
0!
#399
b10000110 ,
1!
#400
0!
#401
b10001000 ,
1!
#402
0!
#403
b10001010 ,
1!
#404
0!
#405
b10001100 ,
1!
#406
0!
#407
b10001110 ,
1!
#408
0!
#409
b10010000 ,
1!
#410
0!
#411
b10010010 ,
1!
#412
0!
#413
b10010100 ,
1!
#414
0!
#415
b10010110 ,
1!
#416
0!
#417
b10011000 ,
1!
#418
0!
#419
b10011010 ,
1!
#420
0!
#421
b10011100 ,
1!
#422
0!
#423
b10011110 ,
1!
#424
0!
#425
b10100000 ,
1!
#426
0!
#427
b10100010 ,
1!
#428
0!
#429
b10100100 ,
1!
#430
0!
#431
b10100110 ,
1!
#432
0!
#433
b10101000 ,
1!
#434
0!
#435
b10101010 ,
1!
#436
0!
#437
b10101100 ,
1!
#438
0!
#439
b10101110 ,
1!
#440
0!
#441
b10110000 ,
1!
#442
0!
#443
b10110010 ,
1!
#444
0!
#445
b10110100 ,
1!
#446
0!
#447
b10110110 ,
1!
#448
0!
#449
b10111000 ,
1!
#450
0!
#451
b10111010 ,
1!
#452
0!
#453
b10111100 ,
1!
#454
0!
#455
b10111110 ,
1!
#456
0!
#457
b11000000 ,
1!
#458
0!
#459
b11000010 ,
1!
#460
0!
#461
b11000100 ,
1!
#462
0!
#463
b11000110 ,
1!
#464
0!
#465
b11001000 ,
1!
#466
0!
#467
b11001010 ,
1!
#468
0!
#469
b11001100 ,
1!
#470
0!
#471
b11001110 ,
1!
#472
0!
#473
b11010000 ,
1!
#474
0!
#475
b11010010 ,
1!
#476
0!
#477
b11010100 ,
1!
#478
0!
#479
b11010110 ,
1!
#480
0!
#481
b11011000 ,
1!
#482
0!
#483
b11011010 ,
1!
#484
0!
#485
b11011100 ,
1!
#486
0!
#487
b11011110 ,
1!
#488
0!
#489
b11100000 ,
1!
#490
0!
#491
b11100010 ,
1!
#492
0!
#493
b11100100 ,
1!
#494
0!
#495
b11100110 ,
1!
#496
0!
#497
b11101000 ,
1!
#498
0!
#499
b11101010 ,
1!
#500
0!
#501
b11101100 ,
1!
#502
0!
#503
b11101110 ,
1!
#504
0!
#505
b11110000 ,
1!
#506
0!
#507
b11110010 ,
1!
#508
0!
#509
b11110100 ,
1!
#510
0!
#511
b11110110 ,
1!
#512
0!
#513
b11111000 ,
1!
#514
0!
#515
b11111010 ,
1!
#516
0!
#517
b11111100 ,
1!
#518
0!
#519
b11111110 ,
1!
#520
0!
#521
b0 ,
1!
#522
0!
#523
b10 ,
1!
#524
0!
#525
b100 ,
1!
#526
0!
#527
b110 ,
1!
#528
0!
#529
b1000 ,
1!
#530
0!
#531
b1010 ,
1!
#532
0!
#533
b1100 ,
1!
#534
0!
#535
b1110 ,
1!
#536
0!
#537
b10000 ,
1!
#538
0!
#539
b10010 ,
1!
#540
0!
#541
b10100 ,
1!
#542
0!
#543
b10110 ,
1!
#544
0!
#545
b11000 ,
1!
#546
0!
#547
b11010 ,
1!
#548
0!
#549
b11100 ,
1!
#550
0!
#551
b11110 ,
1!
#552
0!
#553
b100000 ,
1!
#554
0!
#555
b100010 ,
1!
#556
0!
#557
b100100 ,
1!
#558
0!
#559
b100110 ,
1!
#560
0!
#561
b101000 ,
1!
#562
0!
#563
b101010 ,
1!
#564
0!
#565
b101100 ,
1!
#566
0!
#567
b101110 ,
1!
#568
0!
#569
b110000 ,
1!
#570
0!
#571
b110010 ,
1!
#572
0!
#573
b110100 ,
1!
#574
0!
#575
b110110 ,
1!
#576
0!
#577
b111000 ,
1!
#578
0!
#579
b111010 ,
1!
#580
0!
#581
b111100 ,
1!
#582
0!
#583
b111110 ,
1!
#584
0!
#585
b1000000 ,
1!
#586
0!
#587
b1000010 ,
1!
#588
0!
#589
b1000100 ,
1!
#590
0!
#591
b1000110 ,
1!
#592
0!
#593
b1001000 ,
1!
#594
0!
#595
b1001010 ,
1!
#596
0!
#597
b1001100 ,
1!
#598
0!
#599
b1001110 ,
1!
#600
0!
#601
b1010000 ,
1!
#602
0!
#603
b1010010 ,
1!
#604
0!
#605
b1010100 ,
1!
#606
0!
#607
b1010110 ,
1!
#608
0!
#609
b1011000 ,
1!
#610
0!
#611
b1011010 ,
1!
#612
0!
#613
b1011100 ,
1!
#614
0!
#615
b1011110 ,
1!
#616
0!
#617
b1100000 ,
1!
#618
0!
#619
b1100010 ,
1!
#620
0!
#621
b1100100 ,
1!
#622
0!
#623
b1100110 ,
1!
#624
0!
#625
b1101000 ,
1!
#626
0!
#627
b1101010 ,
1!
#628
0!
#629
b1101100 ,
1!
#630
0!
#631
b1101110 ,
1!
#632
0!
#633
b1110000 ,
1!
#634
0!
#635
b1110010 ,
1!
#636
0!
#637
b1110100 ,
1!
#638
0!
#639
b1110110 ,
1!
#640
0!
#641
b1111000 ,
1!
#642
0!
#643
b1111010 ,
1!
#644
0!
#645
b1111100 ,
1!
#646
0!
#647
b1111110 ,
1!
#648
0!
#649
b10000000 ,
1!
#650
0!
#651
b10000010 ,
1!
#652
0!
#653
b10000100 ,
1!
#654
0!
#655
b10000110 ,
1!
#656
0!
#657
b10001000 ,
1!
#658
0!
#659
b10001010 ,
1!
#660
0!
#661
b10001100 ,
1!
#662
0!
#663
b10001110 ,
1!
#664
0!
#665
b10010000 ,
1!
#666
0!
#667
b10010010 ,
1!
#668
0!
#669
b10010100 ,
1!
#670
0!
#671
b10010110 ,
1!
#672
0!
#673
b10011000 ,
1!
#674
0!
#675
b10011010 ,
1!
#676
0!
#677
b10011100 ,
1!
#678
0!
#679
b10011110 ,
1!
#680
0!
#681
b10100000 ,
1!
#682
0!
#683
b10100010 ,
1!
#684
0!
#685
b10100100 ,
1!
#686
0!
#687
b10100110 ,
1!
#688
0!
#689
b10101000 ,
1!
#690
0!
#691
b10101010 ,
1!
#692
0!
#693
b10101100 ,
1!
#694
0!
#695
b10101110 ,
1!
#696
0!
#697
b10110000 ,
1!
#698
0!
#699
b10110010 ,
1!
#700
0!
#701
b10110100 ,
1!
#702
0!
#703
b10110110 ,
1!
#704
0!
#705
b10111000 ,
1!
#706
0!
#707
b10111010 ,
1!
#708
0!
#709
b10111100 ,
1!
#710
0!
#711
b10111110 ,
1!
#712
0!
#713
b11000000 ,
1!
#714
0!
#715
b11000010 ,
1!
#716
0!
#717
b11000100 ,
1!
#718
0!
#719
b11000110 ,
1!
#720
0!
#721
b11001000 ,
1!
#722
0!
#723
b11001010 ,
1!
#724
0!
#725
b11001100 ,
1!
#726
0!
#727
b11001110 ,
1!
#728
0!
#729
b11010000 ,
1!
#730
0!
#731
b11010010 ,
1!
#732
0!
#733
b11010100 ,
1!
#734
0!
#735
b11010110 ,
1!
#736
0!
#737
b11011000 ,
1!
#738
0!
#739
b11011010 ,
1!
#740
0!
#741
b11011100 ,
1!
#742
0!
#743
b11011110 ,
1!
#744
0!
#745
b11100000 ,
1!
#746
0!
#747
b11100010 ,
1!
#748
0!
#749
b11100100 ,
1!
#750
0!
#751
b11100110 ,
1!
#752
0!
#753
b11101000 ,
1!
#754
0!
#755
b11101010 ,
1!
#756
0!
#757
b11101100 ,
1!
#758
0!
#759
b11101110 ,
1!
#760
0!
#761
b11110000 ,
1!
#762
0!
#763
b11110010 ,
1!
#764
0!
#765
b11110100 ,
1!
#766
0!
#767
b11110110 ,
1!
#768
0!
#769
b11111000 ,
1!
#770
0!
#771
b11111010 ,
1!
#772
0!
#773
b11111100 ,
1!
#774
0!
#775
b11111110 ,
1!
#776
0!
#777
b0 ,
1!
#778
0!
#779
b10 ,
1!
#780
0!
#781
b100 ,
1!
#782
0!
#783
b110 ,
1!
#784
0!
#785
b1000 ,
1!
#786
0!
#787
b1010 ,
1!
#788
0!
#789
b1100 ,
1!
#790
0!
#791
b1110 ,
1!
#792
0!
#793
b10000 ,
1!
#794
0!
#795
b10010 ,
1!
#796
0!
#797
b10100 ,
1!
#798
0!
#799
b10110 ,
1!
#800
0!
#801
b11000 ,
1!
#802
0!
#803
b11010 ,
1!
#804
0!
#805
b11100 ,
1!
#806
0!
#807
b11110 ,
1!
#808
0!
#809
b100000 ,
1!
#810
0!
#811
b100010 ,
1!
#812
0!
#813
b100100 ,
1!
#814
0!
#815
b100110 ,
1!
#816
0!
#817
b101000 ,
1!
#818
0!
#819
b101010 ,
1!
#820
0!
#821
b101100 ,
1!
#822
0!
#823
b101110 ,
1!
#824
0!
#825
b110000 ,
1!
#826
0!
#827
b110010 ,
1!
#828
0!
#829
b110100 ,
1!
#830
0!
#831
b110110 ,
1!
#832
0!
#833
b111000 ,
1!
#834
0!
#835
b111010 ,
1!
#836
0!
#837
b111100 ,
1!
#838
0!
#839
b111110 ,
1!
#840
0!
#841
b1000000 ,
1!
#842
0!
#843
b1000010 ,
1!
#844
0!
#845
b1000100 ,
1!
#846
0!
#847
b1000110 ,
1!
#848
0!
#849
b1001000 ,
1!
#850
0!
#851
b1001010 ,
1!
#852
0!
#853
b1001100 ,
1!
#854
0!
#855
b1001110 ,
1!
#856
0!
#857
b1010000 ,
1!
#858
0!
#859
b1010010 ,
1!
#860
0!
#861
b1010100 ,
1!
#862
0!
#863
b1010110 ,
1!
#864
0!
#865
b1011000 ,
1!
#866
0!
#867
b1011010 ,
1!
#868
0!
#869
b1011100 ,
1!
#870
0!
#871
b1011110 ,
1!
#872
0!
#873
b1100000 ,
1!
#874
0!
#875
b1100010 ,
1!
#876
0!
#877
b1100100 ,
1!
#878
0!
#879
b1100110 ,
1!
#880
0!
#881
b1101000 ,
1!
#882
0!
#883
b1101010 ,
1!
#884
0!
#885
b1101100 ,
1!
#886
0!
#887
b1101110 ,
1!
#888
0!
#889
b1110000 ,
1!
#890
0!
#891
b1110010 ,
1!
#892
0!
#893
b1110100 ,
1!
#894
0!
#895
b1110110 ,
1!
#896
0!
#897
b1111000 ,
1!
#898
0!
#899
b1111010 ,
1!
#900
0!
#901
b1111100 ,
1!
#902
0!
#903
b1111110 ,
1!
#904
0!
#905
b10000000 ,
1!
#906
0!
#907
b10000010 ,
1!
#908
0!
#909
b10000100 ,
1!
#910
0!
#911
b10000110 ,
1!
#912
0!
#913
b10001000 ,
1!
#914
0!
#915
b10001010 ,
1!
#916
0!
#917
b10001100 ,
1!
#918
0!
#919
b10001110 ,
1!
#920
0!
#921
b10010000 ,
1!
#922
0!
#923
b10010010 ,
1!
#924
0!
#925
b10010100 ,
1!
#926
0!
#927
b10010110 ,
1!
#928
0!
#929
b10011000 ,
1!
#930
0!
#931
b10011010 ,
1!
#932
0!
#933
b10011100 ,
1!
#934
0!
#935
b10011110 ,
1!
#936
0!
#937
b10100000 ,
1!
#938
0!
#939
b10100010 ,
1!
#940
0!
#941
b10100100 ,
1!
#942
0!
#943
b10100110 ,
1!
#944
0!
#945
b10101000 ,
1!
#946
0!
#947
b10101010 ,
1!
#948
0!
#949
b10101100 ,
1!
#950
0!
#951
b10101110 ,
1!
#952
0!
#953
b10110000 ,
1!
#954
0!
#955
b10110010 ,
1!
#956
0!
#957
b10110100 ,
1!
#958
0!
#959
b10110110 ,
1!
#960
0!
#961
b10111000 ,
1!
#962
0!
#963
b10111010 ,
1!
#964
0!
#965
b10111100 ,
1!
#966
0!
#967
b10111110 ,
1!
#968
0!
#969
b11000000 ,
1!
#970
0!
#971
b11000010 ,
1!
#972
0!
#973
b11000100 ,
1!
#974
0!
#975
b11000110 ,
1!
#976
0!
#977
b11001000 ,
1!
#978
0!
#979
b11001010 ,
1!
#980
0!
#981
b11001100 ,
1!
#982
0!
#983
b11001110 ,
1!
#984
0!
#985
b11010000 ,
1!
#986
0!
#987
b11010010 ,
1!
#988
0!
#989
b11010100 ,
1!
#990
0!
#991
b11010110 ,
1!
#992
0!
#993
b11011000 ,
1!
#994
0!
#995
b11011010 ,
1!
#996
0!
#997
b11011100 ,
1!
#998
0!
#999
b11011110 ,
1!
#1000
0!
#1001
b11100000 ,
1!
#1002
0!
#1003
b11100010 ,
1!
#1004
0!
#1005
b11100100 ,
1!
#1006
0!
#1007
b11100110 ,
1!
#1008
0!
#1009
b11101000 ,
1!
#1010
0!
#1011
b11101010 ,
1!
#1012
0!
#1013
b11101100 ,
1!
#1014
0!
#1015
b11101110 ,
1!
#1016
0!
#1017
b11110000 ,
1!
#1018
0!
#1019
b11110010 ,
1!
#1020
0!
#1021
b11110100 ,
1!
#1022
0!
#1023
b11110110 ,
1!
#1024
0!
#1025
b11111000 ,
1!
#1026
0!
#1027
b11111010 ,
1!
#1028
0!
#1029
b11111100 ,
1!
#1030
0!
#1031
b11111110 ,
1!
#1032
0!
#1033
b0 ,
1!
#1034
0!
#1035
b10 ,
1!
#1036
0!
#1037
b100 ,
1!
#1038
0!
#1039
b110 ,
1!
#1040
0!
#1041
b1000 ,
1!
#1042
0!
#1043
b1010 ,
1!
#1044
0!
#1045
b1100 ,
1!
#1046
0!
#1047
b1110 ,
1!
#1048
0!
#1049
b10000 ,
1!
#1050
0!
#1051
b10010 ,
1!
#1052
0!
#1053
b10100 ,
1!
#1054
0!
#1055
b10110 ,
1!
#1056
0!
#1057
b11000 ,
1!
#1058
0!
#1059
b11010 ,
1!
#1060
0!
#1061
b11100 ,
1!
#1062
0!
#1063
b11110 ,
1!
#1064
0!
#1065
b100000 ,
1!
#1066
0!
